hsa_reimburse_package_radian21/__init__.py
hsa_reimburse_package_radian21/hsa_reimburse.py
hsa_reimburse-0.4.0.dist-info/LICENSE
hsa_reimburse-0.4.0.dist-info/METADATA
hsa_reimburse-0.4.0.dist-info/WHEEL
hsa_reimburse-0.4.0.dist-info/entry_points.txt
hsa_reimburse-0.4.0.dist-info/top_level.txt
hsa_reimburse-0.4.0.dist-info/RECORD
