Metadata-Version: 2.2
Name: hsa-reimburse
Version: 0.4.0
Summary: HSA Reimbursement CLI is a command-line tool designed to help users manage healthcare receipts of Health Savings Account.
Author-email: Andy Fritsch <radian21@gmail.com>
Maintainer-email: Andy Fritsch <radian21@gmail.com>
Project-URL: Homepage, https://github.com/radian21/hsa_reimburse
Project-URL: Issues, https://github.com/radian21/hsa_reimburse/issues
Classifier: Programming Language :: Python :: 3
Classifier: License :: OSI Approved :: MIT License
Classifier: Operating System :: OS Independent
Requires-Python: >=3.8
License-File: LICENSE
Dynamic: requires-python
